{
	"configurations" : 
	[
		{
			"directories" : 
			[
				{
					"build" : ".",
					"jsonFile" : "directory-.-Debug-d0094a50bb2071803777.json",
					"minimumCMakeVersion" : 
					{
						"string" : "3.27"
					},
					"projectIndex" : 0,
					"source" : ".",
					"targetIndexes" : 
					[
						0
					]
				}
			],
			"name" : "Debug",
			"projects" : 
			[
				{
					"directoryIndexes" : 
					[
						0
					],
					"name" : "EvaluationJeux",
					"targetIndexes" : 
					[
						0
					]
				}
			],
			"targets" : 
			[
				{
					"directoryIndex" : 0,
					"id" : "EvaluationJeux::@6890427a1f51a3e7e1df",
					"jsonFile" : "target-EvaluationJeux-Debug-3c729348cc76440896ca.json",
					"name" : "EvaluationJeux",
					"projectIndex" : 0
				}
			]
		}
	],
	"kind" : "codemodel",
	"paths" : 
	{
		"build" : "C:/Users/Doria/Desktop/Module 4 Fichiers/Exo/EvaluationJeux/cmake-build-debug",
		"source" : "C:/Users/Doria/Desktop/Module 4 Fichiers/Exo/EvaluationJeux"
	},
	"version" : 
	{
		"major" : 2,
		"minor" : 6
	}
}
